jw_rpcm/__about__.py
jw_rpcm/__init__.py
jw_rpcm/geo.py
jw_rpcm/rpc_file_readers.py
jw_rpcm/rpc_model.py
jw_rpcm/utils.py
jw_rpcm-0.0.3.dist-info/LICENSE
jw_rpcm-0.0.3.dist-info/METADATA
jw_rpcm-0.0.3.dist-info/WHEEL
jw_rpcm-0.0.3.dist-info/entry_points.txt
jw_rpcm-0.0.3.dist-info/top_level.txt
jw_rpcm-0.0.3.dist-info/RECORD
