Metadata-Version: 2.1
Name: jw-rpcm
Version: 0.0.3
Summary: Rational Polynomial Camera Model for optical satellite images.
Home-page: https://github.com/JaeWangL/rpcm
Download-URL: https://pypi.org/project/jw-rpcm
Author: JaeWang Lee
Author-email: JaeWangL <jnso5072@outlook.kr>
Project-URL: Bug Tracker, https://github.com/JaeWangL/rpcm/issues
Project-URL: Source Code, https://github.com/JaeWangL/rpcm
Requires-Python: >=3.6
License-File: LICENSE
Requires-Dist: numpy
Requires-Dist: pyproj
Requires-Dist: geojson
Requires-Dist: rasterio[s3] (>=1.2)
Requires-Dist: srtm4 (>=1.0.2)
Provides-Extra: test
Requires-Dist: pytest ; extra == 'test'
